Lab3/components_dev/universalClockDivider/clkDiv_test.v
module clkDiv #(
    parameter clkInFreq = 100_000_000, // Input clock frequency (default: 100MHz)
    parameter tgtFreq = 1              // Target output clock frequency (default: 1Hz)
) (
    input clk_in,
    input rst_n,
    output reg clk_out = 0
);

    // Calculate the divider value.  We divide by 2 * target hz because we toggle
    // clk_out, effectively creating a 50% duty cycle.
    localparam divParm = clkInFreq / (2 * tgtFreq);

    // Determine the required counter width (number of bits)
    localparam COUNTER_WIDTH = $clog2(divParm);

    reg [COUNTER_WIDTH-1:0] counter = 0;


    always @(posedge clk_in or negedge rst_n) begin
        if (!rst_n) begin
            counter <= 0;
            clk_out <= 0;
        end else begin
            if (counter == divParm - 1) begin
                counter <= 0;
                clk_out <= ~clk_out; // Toggle clk_out
            end else begin
                counter <= counter + 1;
            end
        end
    end

endmodule

Lab3/components_dev/universalClockDivider/clkDiv_test_tb2.v
`timescale 1ns / 1ps
module clkDiv_tb;

    // Input clock frequency (fixed)
    parameter CLK_IN_FREQ = 100_000_000; // 100 MHz

    // Target frequencies (multiple instances)
    parameter TARGET_FREQ_1  = 50_000_000;  // 50 MHz (20 ns period)
    parameter TARGET_FREQ_2  = 25_000_000; // 25 MHz (40 ns period)
    parameter TARGET_FREQ_3  = 10_000_000; // 10 MHz (100 ns period)
    parameter TARGET_FREQ_4  = 5_000_000;  //  5 MHz (200 ns period)
    parameter TARGET_FREQ_5  = 2_000_000;    //  2 MHz (500 ns period)
    parameter TARGET_FREQ_6 = 1_000_000; // 1 MHz (1000 ns period)
    parameter TARGET_FREQ_7 = 500_000;    // 500 KHz (2000ns period)
    // Add more target frequencies as needed

    // Signals
    reg clk_in;
    reg rst_n;
    wire clk_out_1;
    wire clk_out_2;
    wire clk_out_3;
    wire clk_out_4;
    wire clk_out_5;
    wire clk_out_6;
    wire clk_out_7;

    // Instantiate multiple clkDiv instances
    clkDiv #(
        .clkInFreq(CLK_IN_FREQ),
        .tgtFreq(TARGET_FREQ_1)
    ) dut1 (
        .clk_in(clk_in),
        .rst_n(rst_n),
        .clk_out(clk_out_1)
    );

    clkDiv #(
        .clkInFreq(CLK_IN_FREQ),
        .tgtFreq(TARGET_FREQ_2)
    ) dut2 (
        .clk_in(clk_in),
        .rst_n(rst_n),
        .clk_out(clk_out_2)
    );

    clkDiv #(
        .clkInFreq(CLK_IN_FREQ),
        .tgtFreq(TARGET_FREQ_3)
    ) dut3 (
        .clk_in(clk_in),
        .rst_n(rst_n),
        .clk_out(clk_out_3)
    );

    clkDiv #(
        .clkInFreq(CLK_IN_FREQ),
        .tgtFreq(TARGET_FREQ_4)
    ) dut4 (
        .clk_in(clk_in),
        .rst_n(rst_n),
        .clk_out(clk_out_4)
    );

    clkDiv #(
        .clkInFreq(CLK_IN_FREQ),
        .tgtFreq(TARGET_FREQ_5)
    ) dut5 (
        .clk_in(clk_in),
        .rst_n(rst_n),
        .clk_out(clk_out_5)
    );

    clkDiv #(
        .clkInFreq(CLK_IN_FREQ),
        .tgtFreq(TARGET_FREQ_6)
    ) dut6 (
        .clk_in(clk_in),
        .rst_n(rst_n),
        .clk_out(clk_out_6)
    );
    
    clkDiv #(
        .clkInFreq(CLK_IN_FREQ),
        .tgtFreq(TARGET_FREQ_7)
    ) dut7 (
        .clk_in(clk_in),
        .rst_n(rst_n),
        .clk_out(clk_out_7)
    );


    // Clock generation (100 MHz)
    initial begin
        clk_in = 0;
        forever #5 clk_in = ~clk_in; // 10 ns period = 100 MHz
    end

    // Test sequence
    initial begin
        // 1. Reset
        rst_n = 0;
        #20;        // Hold reset for 20 ns
        rst_n = 1;
        #20;        // Wait a bit after reset

        // 2. Observe clk_out signals for a few cycles
        #5000;      // Observe for 5000 ns (5 us) - adjust as needed

        // 3. Apply another reset pulse
        rst_n = 0;
        #10;
        rst_n = 1;

        // 4. Observe clk_out signals again
        #5000;      // Observe for another 5000 ns (5 us)

        // 5. Finish simulation
        $finish;
    end

      // Optional: Monitor signals for debugging
    initial begin
        $dumpfile("clkDiv_tb2.vcd");
        $dumpvars(0, clkDiv_tb);
    end

     // Timescale directive
    

endmodule

Lab3/components_dev/universalClockDivider/clkDiv_tb2.vcd
$date
	Thu Mar 13 06:11:39 2025
$end
$version
	Icarus Verilog
$end
$timescale
	1ps
$end
$scope module clkDiv_tb $end
$var wire 1 ! clk_out_7 $end
$var wire 1 " clk_out_6 $end
$var wire 1 # clk_out_5 $end
$var wire 1 $ clk_out_4 $end
$var wire 1 % clk_out_3 $end
$var wire 1 & clk_out_2 $end
$var wire 1 ' clk_out_1 $end
$var parameter 32 ( CLK_IN_FREQ $end
$var parameter 32 ) TARGET_FREQ_1 $end
$var parameter 32 * TARGET_FREQ_2 $end
$var parameter 32 + TARGET_FREQ_3 $end
$var parameter 32 , TARGET_FREQ_4 $end
$var parameter 32 - TARGET_FREQ_5 $end
$var parameter 32 . TARGET_FREQ_6 $end
$var parameter 32 / TARGET_FREQ_7 $end
$var reg 1 0 clk_in $end
$var reg 1 1 rst_n $end
$scope module dut1 $end
$var wire 1 0 clk_in $end
$var wire 1 1 rst_n $end
$var parameter 32 2 COUNTER_WIDTH $end
$var parameter 32 3 clkInFreq $end
$var parameter 64 4 divParm $end
$var parameter 32 5 tgtFreq $end
$var reg 1 ' clk_out $end
$var reg 2 6 counter [-1:0] $end
$upscope $end
$scope module dut2 $end
$var wire 1 0 clk_in $end
$var wire 1 1 rst_n $end
$var parameter 32 7 COUNTER_WIDTH $end
$var parameter 32 8 clkInFreq $end
$var parameter 64 9 divParm $end
$var parameter 32 : tgtFreq $end
$var reg 1 & clk_out $end
$var reg 1 ; counter $end
$upscope $end
$scope module dut3 $end
$var wire 1 0 clk_in $end
$var wire 1 1 rst_n $end
$var parameter 32 < COUNTER_WIDTH $end
$var parameter 32 = clkInFreq $end
$var parameter 64 > divParm $end
$var parameter 32 ? tgtFreq $end
$var reg 1 % clk_out $end
$var reg 3 @ counter [2:0] $end
$upscope $end
$scope module dut4 $end
$var wire 1 0 clk_in $end
$var wire 1 1 rst_n $end
$var parameter 32 A COUNTER_WIDTH $end
$var parameter 32 B clkInFreq $end
$var parameter 64 C divParm $end
$var parameter 32 D tgtFreq $end
$var reg 1 $ clk_out $end
$var reg 4 E counter [3:0] $end
$upscope $end
$scope module dut5 $end
$var wire 1 0 clk_in $end
$var wire 1 1 rst_n $end
$var parameter 32 F COUNTER_WIDTH $end
$var parameter 32 G clkInFreq $end
$var parameter 64 H divParm $end
$var parameter 32 I tgtFreq $end
$var reg 1 # clk_out $end
$var reg 5 J counter [4:0] $end
$upscope $end
$scope module dut6 $end
$var wire 1 0 clk_in $end
$var wire 1 1 rst_n $end
$var parameter 32 K COUNTER_WIDTH $end
$var parameter 32 L clkInFreq $end
$var parameter 64 M divParm $end
$var parameter 32 N tgtFreq $end
$var reg 1 " clk_out $end
$var reg 6 O counter [5:0] $end
$upscope $end
$scope module dut7 $end
$var wire 1 0 clk_in $end
$var wire 1 1 rst_n $end
$var parameter 32 P COUNTER_WIDTH $end
$var parameter 32 Q clkInFreq $end
$var parameter 64 R divParm $end
$var parameter 32 S tgtFreq $end
$var reg 1 ! clk_out $end
$var reg 7 T counter [6:0] $end
$upscope $end
$upscope $end
$enddefinitions $end
$comment Show the parameter values. $end
$dumpall
b1111010000100100000 S
b1100100 R
b101111101011110000100000000 Q
b111 P
b11110100001001000000 N
b110010 M
b101111101011110000100000000 L
b110 K
b111101000010010000000 I
b11001 H
b101111101011110000100000000 G
b101 F
b10011000100101101000000 D
b1010 C
b101111101011110000100000000 B
b100 A
b100110001001011010000000 ?
b101 >
b101111101011110000100000000 =
b11 <
b1011111010111100001000000 :
b10 9
b101111101011110000100000000 8
b1 7
b10111110101111000010000000 5
b1 4
b101111101011110000100000000 3
b0 2
b1111010000100100000 /
b11110100001001000000 .
b111101000010010000000 -
b10011000100101101000000 ,
b100110001001011010000000 +
b1011111010111100001000000 *
b10111110101111000010000000 )
b101111101011110000100000000 (
$end
#0
$dumpvars
b0 T
b0 O
b0 J
b0 E
b0 @
0;
b0 6
01
00
0'
0&
0%
0$
0#
0"
0!
$end
#5000
10
#10000
00
#15000
10
#20000
00
11
#25000
b1 T
b1 O
b1 J
b1 E
b1 @
1;
1'
10
#30000
00
#35000
0'
1&
0;
b10 @
b10 E
b10 J
b10 O
b10 T
10
#40000
00
#45000
b11 T
b11 O
b11 J
b11 E
b11 @
1;
1'
10
#50000
00
#55000
0'
0&
0;
b100 @
b100 E
b100 J
b100 O
b100 T
10
#60000
00
#65000
b101 T
b101 O
b101 J
b101 E
1%
b0 @
1;
1'
10
#70000
00
#75000
0'
1&
0;
b1 @
b110 E
b110 J
b110 O
b110 T
10
#80000
00
#85000
b111 T
b111 O
b111 J
b111 E
b10 @
1;
1'
10
#90000
00
#95000
0'
0&
0;
b11 @
b1000 E
b1000 J
b1000 O
b1000 T
10
#100000
00
#105000
b1001 T
b1001 O
b1001 J
b1001 E
b100 @
1;
1'
10
#110000
00
#115000
0'
1&
0;
0%
b0 @
1$
b0 E
b1010 J
b1010 O
b1010 T
10
#120000
00
#125000
b1011 T
b1011 O
b1011 J
b1 E
b1 @
1;
1'
10
#130000
00
#135000
0'
0&
0;
b10 @
b10 E
b1100 J
b1100 O
b1100 T
10
#140000
00
#145000
b1101 T
b1101 O
b1101 J
b11 E
b11 @
1;
1'
10
#150000
00
#155000
0'
1&
0;
b100 @
b100 E
b1110 J
b1110 O
b1110 T
10
#160000
00
#165000
b1111 T
b1111 O
b1111 J
b101 E
1%
b0 @
1;
1'
10
#170000
00
#175000
0'
0&
0;
b1 @
b110 E
b10000 J
b10000 O
b10000 T
10
#180000
00
#185000
b10001 T
b10001 O
b10001 J
b111 E
b10 @
1;
1'
10
#190000
00
#195000
0'
1&
0;
b11 @
b1000 E
b10010 J
b10010 O
b10010 T
10
#200000
00
#205000
b10011 T
b10011 O
b10011 J
b1001 E
b100 @
1;
1'
10
#210000
00
#215000
0'
0&
0;
0%
b0 @
0$
b0 E
b10100 J
b10100 O
b10100 T
10
#220000
00
#225000
b10101 T
b10101 O
b10101 J
b1 E
b1 @
1;
1'
10
#230000
00
#235000
0'
1&
0;
b10 @
b10 E
b10110 J
b10110 O
b10110 T
10
#240000
00
#245000
b10111 T
b10111 O
b10111 J
b11 E
b11 @
1;
1'
10
#250000
00
#255000
0'
0&
0;
b100 @
b100 E
b11000 J
b11000 O
b11000 T
10
#260000
00
#265000
b11001 T
b11001 O
1#
b0 J
b101 E
1%
b0 @
1;
1'
10
#270000
00
#275000
0'
1&
0;
b1 @
b110 E
b1 J
b11010 O
b11010 T
10
#280000
00
#285000
b11011 T
b11011 O
b10 J
b111 E
b10 @
1;
1'
10
#290000
00
#295000
0'
0&
0;
b11 @
b1000 E
b11 J
b11100 O
b11100 T
10
#300000
00
#305000
b11101 T
b11101 O
b100 J
b1001 E
b100 @
1;
1'
10
#310000
00
#315000
0'
1&
0;
0%
b0 @
1$
b0 E
b101 J
b11110 O
b11110 T
10
#320000
00
#325000
b11111 T
b11111 O
b110 J
b1 E
b1 @
1;
1'
10
#330000
00
#335000
0'
0&
0;
b10 @
b10 E
b111 J
b100000 O
b100000 T
10
#340000
00
#345000
b100001 T
b100001 O
b1000 J
b11 E
b11 @
1;
1'
10
#350000
00
#355000
0'
1&
0;
b100 @
b100 E
b1001 J
b100010 O
b100010 T
10
#360000
00
#365000
b100011 T
b100011 O
b1010 J
b101 E
1%
b0 @
1;
1'
10
#370000
00
#375000
0'
0&
0;
b1 @
b110 E
b1011 J
b100100 O
b100100 T
10
#380000
00
#385000
b100101 T
b100101 O
b1100 J
b111 E
b10 @
1;
1'
10
#390000
00
#395000
0'
1&
0;
b11 @
b1000 E
b1101 J
b100110 O
b100110 T
10
#400000
00
#405000
b100111 T
b100111 O
b1110 J
b1001 E
b100 @
1;
1'
10
#410000
00
#415000
0'
0&
0;
0%
b0 @
0$
b0 E
b1111 J
b101000 O
b101000 T
10
#420000
00
#425000
b101001 T
b101001 O
b10000 J
b1 E
b1 @
1;
1'
10
#430000
00
#435000
0'
1&
0;
b10 @
b10 E
b10001 J
b101010 O
b101010 T
10
#440000
00
#445000
b101011 T
b101011 O
b10010 J
b11 E
b11 @
1;
1'
10
#450000
00
#455000
0'
0&
0;
b100 @
b100 E
b10011 J
b101100 O
b101100 T
10
#460000
00
#465000
b101101 T
b101101 O
b10100 J
b101 E
1%
b0 @
1;
1'
10
#470000
00
#475000
0'
1&
0;
b1 @
b110 E
b10101 J
b101110 O
b101110 T
10
#480000
00
#485000
b101111 T
b101111 O
b10110 J
b111 E
b10 @
1;
1'
10
#490000
00
#495000
0'
0&
0;
b11 @
b1000 E
b10111 J
b110000 O
b110000 T
10
#500000
00
#505000
b110001 T
b110001 O
b11000 J
b1001 E
b100 @
1;
1'
10
#510000
00
#515000
0'
1&
0;
0%
b0 @
1$
b0 E
0#
b0 J
1"
b0 O
b110010 T
10
#520000
00
#525000
b110011 T
b1 O
b1 J
b1 E
b1 @
1;
1'
10
#530000
00
#535000
0'
0&
0;
b10 @
b10 E
b10 J
b10 O
b110100 T
10
#540000
00
#545000
b110101 T
b11 O
b11 J
b11 E
b11 @
1;
1'
10
#550000
00
#555000
0'
1&
0;
b100 @
b100 E
b100 J
b100 O
b110110 T
10
#560000
00
#565000
b110111 T
b101 O
b101 J
b101 E
1%
b0 @
1;
1'
10
#570000
00
#575000
0'
0&
0;
b1 @
b110 E
b110 J
b110 O
b111000 T
10
#580000
00
#585000
b111001 T
b111 O
b111 J
b111 E
b10 @
1;
1'
10
#590000
00
#595000
0'
1&
0;
b11 @
b1000 E
b1000 J
b1000 O
b111010 T
10
#600000
00
#605000
b111011 T
b1001 O
b1001 J
b1001 E
b100 @
1;
1'
10
#610000
00
#615000
0'
0&
0;
0%
b0 @
0$
b0 E
b1010 J
b1010 O
b111100 T
10
#620000
00
#625000
b111101 T
b1011 O
b1011 J
b1 E
b1 @
1;
1'
10
#630000
00
#635000
0'
1&
0;
b10 @
b10 E
b1100 J
b1100 O
b111110 T
10
#640000
00
#645000
b111111 T
b1101 O
b1101 J
b11 E
b11 @
1;
1'
10
#650000
00
#655000
0'
0&
0;
b100 @
b100 E
b1110 J
b1110 O
b1000000 T
10
#660000
00
#665000
b1000001 T
b1111 O
b1111 J
b101 E
1%
b0 @
1;
1'
10
#670000
00
#675000
0'
1&
0;
b1 @
b110 E
b10000 J
b10000 O
b1000010 T
10
#680000
00
#685000
b1000011 T
b10001 O
b10001 J
b111 E
b10 @
1;
1'
10
#690000
00
#695000
0'
0&
0;
b11 @
b1000 E
b10010 J
b10010 O
b1000100 T
10
#700000
00
#705000
b1000101 T
b10011 O
b10011 J
b1001 E
b100 @
1;
1'
10
#710000
00
#715000
0'
1&
0;
0%
b0 @
1$
b0 E
b10100 J
b10100 O
b1000110 T
10
#720000
00
#725000
b1000111 T
b10101 O
b10101 J
b1 E
b1 @
1;
1'
10
#730000
00
#735000
0'
0&
0;
b10 @
b10 E
b10110 J
b10110 O
b1001000 T
10
#740000
00
#745000
b1001001 T
b10111 O
b10111 J
b11 E
b11 @
1;
1'
10
#750000
00
#755000
0'
1&
0;
b100 @
b100 E
b11000 J
b11000 O
b1001010 T
10
#760000
00
#765000
b1001011 T
b11001 O
1#
b0 J
b101 E
1%
b0 @
1;
1'
10
#770000
00
#775000
0'
0&
0;
b1 @
b110 E
b1 J
b11010 O
b1001100 T
10
#780000
00
#785000
b1001101 T
b11011 O
b10 J
b111 E
b10 @
1;
1'
10
#790000
00
#795000
0'
1&
0;
b11 @
b1000 E
b11 J
b11100 O
b1001110 T
10
#800000
00
#805000
b1001111 T
b11101 O
b100 J
b1001 E
b100 @
1;
1'
10
#810000
00
#815000
0'
0&
0;
0%
b0 @
0$
b0 E
b101 J
b11110 O
b1010000 T
10
#820000
00
#825000
b1010001 T
b11111 O
b110 J
b1 E
b1 @
1;
1'
10
#830000
00
#835000
0'
1&
0;
b10 @
b10 E
b111 J
b100000 O
b1010010 T
10
#840000
00
#845000
b1010011 T
b100001 O
b1000 J
b11 E
b11 @
1;
1'
10
#850000
00
#855000
0'
0&
0;
b100 @
b100 E
b1001 J
b100010 O
b1010100 T
10
#860000
00
#865000
b1010101 T
b100011 O
b1010 J
b101 E
1%
b0 @
1;
1'
10
#870000
00
#875000
0'
1&
0;
b1 @
b110 E
b1011 J
b100100 O
b1010110 T
10
#880000
00
#885000
b1010111 T
b100101 O
b1100 J
b111 E
b10 @
1;
1'
10
#890000
00
#895000
0'
0&
0;
b11 @
b1000 E
b1101 J
b100110 O
b1011000 T
10
#900000
00
#905000
b1011001 T
b100111 O
b1110 J
b1001 E
b100 @
1;
1'
10
#910000
00
#915000
0'
1&
0;
0%
b0 @
1$
b0 E
b1111 J
b101000 O
b1011010 T
10
#920000
00
#925000
b1011011 T
b101001 O
b10000 J
b1 E
b1 @
1;
1'
10
#930000
00
#935000
0'
0&
0;
b10 @
b10 E
b10001 J
b101010 O
b1011100 T
10
#940000
00
#945000
b1011101 T
b101011 O
b10010 J
b11 E
b11 @
1;
1'
10
#950000
00
#955000
0'
1&
0;
b100 @
b100 E
b10011 J
b101100 O
b1011110 T
10
#960000
00
#965000
b1011111 T
b101101 O
b10100 J
b101 E
1%
b0 @
1;
1'
10
#970000
00
#975000
0'
0&
0;
b1 @
b110 E
b10101 J
b101110 O
b1100000 T
10
#980000
00
#985000
b1100001 T
b101111 O
b10110 J
b111 E
b10 @
1;
1'
10
#990000
00
#995000
0'
1&
0;
b11 @
b1000 E
b10111 J
b110000 O
b1100010 T
10
#1000000
00
#1005000
b1100011 T
b110001 O
b11000 J
b1001 E
b100 @
1;
1'
10
#1010000
00
#1015000
0'
0&
0;
0%
b0 @
0$
b0 E
0#
b0 J
0"
b0 O
1!
b0 T
10
#1020000
00
#1025000
b1 T
b1 O
b1 J
b1 E
b1 @
1;
1'
10
#1030000
00
#1035000
0'
1&
0;
b10 @
b10 E
b10 J
b10 O
b10 T
10
#1040000
00
#1045000
b11 T
b11 O
b11 J
b11 E
b11 @
1;
1'
10
#1050000
00
#1055000
0'
0&
0;
b100 @
b100 E
b100 J
b100 O
b100 T
10
#1060000
00
#1065000
b101 T
b101 O
b101 J
b101 E
1%
b0 @
1;
1'
10
#1070000
00
#1075000
0'
1&
0;
b1 @
b110 E
b110 J
b110 O
b110 T
10
#1080000
00
#1085000
b111 T
b111 O
b111 J
b111 E
b10 @
1;
1'
10
#1090000
00
#1095000
0'
0&
0;
b11 @
b1000 E
b1000 J
b1000 O
b1000 T
10
#1100000
00
#1105000
b1001 T
b1001 O
b1001 J
b1001 E
b100 @
1;
1'
10
#1110000
00
#1115000
0'
1&
0;
0%
b0 @
1$
b0 E
b1010 J
b1010 O
b1010 T
10
#1120000
00
#1125000
b1011 T
b1011 O
b1011 J
b1 E
b1 @
1;
1'
10
#1130000
00
#1135000
0'
0&
0;
b10 @
b10 E
b1100 J
b1100 O
b1100 T
10
#1140000
00
#1145000
b1101 T
b1101 O
b1101 J
b11 E
b11 @
1;
1'
10
#1150000
00
#1155000
0'
1&
0;
b100 @
b100 E
b1110 J
b1110 O
b1110 T
10
#1160000
00
#1165000
b1111 T
b1111 O
b1111 J
b101 E
1%
b0 @
1;
1'
10
#1170000
00
#1175000
0'
0&
0;
b1 @
b110 E
b10000 J
b10000 O
b10000 T
10
#1180000
00
#1185000
b10001 T
b10001 O
b10001 J
b111 E
b10 @
1;
1'
10
#1190000
00
#1195000
0'
1&
0;
b11 @
b1000 E
b10010 J
b10010 O
b10010 T
10
#1200000
00
#1205000
b10011 T
b10011 O
b10011 J
b1001 E
b100 @
1;
1'
10
#1210000
00
#1215000
0'
0&
0;
0%
b0 @
0$
b0 E
b10100 J
b10100 O
b10100 T
10
#1220000
00
#1225000
b10101 T
b10101 O
b10101 J
b1 E
b1 @
1;
1'
10
#1230000
00
#1235000
0'
1&
0;
b10 @
b10 E
b10110 J
b10110 O
b10110 T
10
#1240000
00
#1245000
b10111 T
b10111 O
b10111 J
b11 E
b11 @
1;
1'
10
#1250000
00
#1255000
0'
0&
0;
b100 @
b100 E
b11000 J
b11000 O
b11000 T
10
#1260000
00
#1265000
b11001 T
b11001 O
1#
b0 J
b101 E
1%
b0 @
1;
1'
10
#1270000
00
#1275000
0'
1&
0;
b1 @
b110 E
b1 J
b11010 O
b11010 T
10
#1280000
00
#1285000
b11011 T
b11011 O
b10 J
b111 E
b10 @
1;
1'
10
#1290000
00
#1295000
0'
0&
0;
b11 @
b1000 E
b11 J
b11100 O
b11100 T
10
#1300000
00
#1305000
b11101 T
b11101 O
b100 J
b1001 E
b100 @
1;
1'
10
#1310000
00
#1315000
0'
1&
0;
0%
b0 @
1$
b0 E
b101 J
b11110 O
b11110 T
10
#1320000
00
#1325000
b11111 T
b11111 O
b110 J
b1 E
b1 @
1;
1'
10
#1330000
00
#1335000
0'
0&
0;
b10 @
b10 E
b111 J
b100000 O
b100000 T
10
#1340000
00
#1345000
b100001 T
b100001 O
b1000 J
b11 E
b11 @
1;
1'
10
#1350000
00
#1355000
0'
1&
0;
b100 @
b100 E
b1001 J
b100010 O
b100010 T
10
#1360000
00
#1365000
b100011 T
b100011 O
b1010 J
b101 E
1%
b0 @
1;
1'
10
#1370000
00
#1375000
0'
0&
0;
b1 @
b110 E
b1011 J
b100100 O
b100100 T
10
#1380000
00
#1385000
b100101 T
b100101 O
b1100 J
b111 E
b10 @
1;
1'
10
#1390000
00
#1395000
0'
1&
0;
b11 @
b1000 E
b1101 J
b100110 O
b100110 T
10
#1400000
00
#1405000
b100111 T
b100111 O
b1110 J
b1001 E
b100 @
1;
1'
10
#1410000
00
#1415000
0'
0&
0;
0%
b0 @
0$
b0 E
b1111 J
b101000 O
b101000 T
10
#1420000
00
#1425000
b101001 T
b101001 O
b10000 J
b1 E
b1 @
1;
1'
10
#1430000
00
#1435000
0'
1&
0;
b10 @
b10 E
b10001 J
b101010 O
b101010 T
10
#1440000
00
#1445000
b101011 T
b101011 O
b10010 J
b11 E
b11 @
1;
1'
10
#1450000
00
#1455000
0'
0&
0;
b100 @
b100 E
b10011 J
b101100 O
b101100 T
10
#1460000
00
#1465000
b101101 T
b101101 O
b10100 J
b101 E
1%
b0 @
1;
1'
10
#1470000
00
#1475000
0'
1&
0;
b1 @
b110 E
b10101 J
b101110 O
b101110 T
10
#1480000
00
#1485000
b101111 T
b101111 O
b10110 J
b111 E
b10 @
1;
1'
10
#1490000
00
#1495000
0'
0&
0;
b11 @
b1000 E
b10111 J
b110000 O
b110000 T
10
#1500000
00
#1505000
b110001 T
b110001 O
b11000 J
b1001 E
b100 @
1;
1'
10
#1510000
00
#1515000
0'
1&
0;
0%
b0 @
1$
b0 E
0#
b0 J
1"
b0 O
b110010 T
10
#1520000
00
#1525000
b110011 T
b1 O
b1 J
b1 E
b1 @
1;
1'
10
#1530000
00
#1535000
0'
0&
0;
b10 @
b10 E
b10 J
b10 O
b110100 T
10
#1540000
00
#1545000
b110101 T
b11 O
b11 J
b11 E
b11 @
1;
1'
10
#1550000
00
#1555000
0'
1&
0;
b100 @
b100 E
b100 J
b100 O
b110110 T
10
#1560000
00
#1565000
b110111 T
b101 O
b101 J
b101 E
1%
b0 @
1;
1'
10
#1570000
00
#1575000
0'
0&
0;
b1 @
b110 E
b110 J
b110 O
b111000 T
10
#1580000
00
#1585000
b111001 T
b111 O
b111 J
b111 E
b10 @
1;
1'
10
#1590000
00
#1595000
0'
1&
0;
b11 @
b1000 E
b1000 J
b1000 O
b111010 T
10
#1600000
00
#1605000
b111011 T
b1001 O
b1001 J
b1001 E
b100 @
1;
1'
10
#1610000
00
#1615000
0'
0&
0;
0%
b0 @
0$
b0 E
b1010 J
b1010 O
b111100 T
10
#1620000
00
#1625000
b111101 T
b1011 O
b1011 J
b1 E
b1 @
1;
1'
10
#1630000
00
#1635000
0'
1&
0;
b10 @
b10 E
b1100 J
b1100 O
b111110 T
10
#1640000
00
#1645000
b111111 T
b1101 O
b1101 J
b11 E
b11 @
1;
1'
10
#1650000
00
#1655000
0'
0&
0;
b100 @
b100 E
b1110 J
b1110 O
b1000000 T
10
#1660000
00
#1665000
b1000001 T
b1111 O
b1111 J
b101 E
1%
b0 @
1;
1'
10
#1670000
00
#1675000
0'
1&
0;
b1 @
b110 E
b10000 J
b10000 O
b1000010 T
10
#1680000
00
#1685000
b1000011 T
b10001 O
b10001 J
b111 E
b10 @
1;
1'
10
#1690000
00
#1695000
0'
0&
0;
b11 @
b1000 E
b10010 J
b10010 O
b1000100 T
10
#1700000
00
#1705000
b1000101 T
b10011 O
b10011 J
b1001 E
b100 @
1;
1'
10
#1710000
00
#1715000
0'
1&
0;
0%
b0 @
1$
b0 E
b10100 J
b10100 O
b1000110 T
10
#1720000
00
#1725000
b1000111 T
b10101 O
b10101 J
b1 E
b1 @
1;
1'
10
#1730000
00
#1735000
0'
0&
0;
b10 @
b10 E
b10110 J
b10110 O
b1001000 T
10
#1740000
00
#1745000
b1001001 T
b10111 O
b10111 J
b11 E
b11 @
1;
1'
10
#1750000
00
#1755000
0'
1&
0;
b100 @
b100 E
b11000 J
b11000 O
b1001010 T
10
#1760000
00
#1765000
b1001011 T
b11001 O
1#
b0 J
b101 E
1%
b0 @
1;
1'
10
#1770000
00
#1775000
0'
0&
0;
b1 @
b110 E
b1 J
b11010 O
b1001100 T
10
#1780000
00
#1785000
b1001101 T
b11011 O
b10 J
b111 E
b10 @
1;
1'
10
#1790000
00
#1795000
0'
1&
0;
b11 @
b1000 E
b11 J
b11100 O
b1001110 T
10
#1800000
00
#1805000
b1001111 T
b11101 O
b100 J
b1001 E
b100 @
1;
1'
10
#1810000
00
#1815000
0'
0&
0;
0%
b0 @
0$
b0 E
b101 J
b11110 O
b1010000 T
10
#1820000
00
#1825000
b1010001 T
b11111 O
b110 J
b1 E
b1 @
1;
1'
10
#1830000
00
#1835000
0'
1&
0;
b10 @
b10 E
b111 J
b100000 O
b1010010 T
10
#1840000
00
#1845000
b1010011 T
b100001 O
b1000 J
b11 E
b11 @
1;
1'
10
#1850000
00
#1855000
0'
0&
0;
b100 @
b100 E
b1001 J
b100010 O
b1010100 T
10
#1860000
00
#1865000
b1010101 T
b100011 O
b1010 J
b101 E
1%
b0 @
1;
1'
10
#1870000
00
#1875000
0'
1&
0;
b1 @
b110 E
b1011 J
b100100 O
b1010110 T
10
#1880000
00
#1885000
b1010111 T
b100101 O
b1100 J
b111 E
b10 @
1;
1'
10
#1890000
00
#1895000
0'
0&
0;
b11 @
b1000 E
b1101 J
b100110 O
b1011000 T
10
#1900000
00
#1905000
b1011001 T
b100111 O
b1110 J
b1001 E
b100 @
1;
1'
10
#1910000
00
#1915000
0'
1&
0;
0%
b0 @
1$
b0 E
b1111 J
b101000 O
b1011010 T
10
#1920000
00
#1925000
b1011011 T
b101001 O
b10000 J
b1 E
b1 @
1;
1'
10
#1930000
00
#1935000
0'
0&
0;
b10 @
b10 E
b10001 J
b101010 O
b1011100 T
10
#1940000
00
#1945000
b1011101 T
b101011 O
b10010 J
b11 E
b11 @
1;
1'
10
#1950000
00
#1955000
0'
1&
0;
b100 @
b100 E
b10011 J
b101100 O
b1011110 T
10
#1960000
00
#1965000
b1011111 T
b101101 O
b10100 J
b101 E
1%
b0 @
1;
1'
10
#1970000
00
#1975000
0'
0&
0;
b1 @
b110 E
b10101 J
b101110 O
b1100000 T
10
#1980000
00
#1985000
b1100001 T
b101111 O
b10110 J
b111 E
b10 @
1;
1'
10
#1990000
00
#1995000
0'
1&
0;
b11 @
b1000 E
b10111 J
b110000 O
b1100010 T
10
#2000000
00
#2005000
b1100011 T
b110001 O
b11000 J
b1001 E
b100 @
1;
1'
10
#2010000
00
#2015000
0'
0&
0;
0%
b0 @
0$
b0 E
0#
b0 J
0"
b0 O
0!
b0 T
10
#2020000
00
#2025000
b1 T
b1 O
b1 J
b1 E
b1 @
1;
1'
10
#2030000
00
#2035000
0'
1&
0;
b10 @
b10 E
b10 J
b10 O
b10 T
10
#2040000
00
#2045000
b11 T
b11 O
b11 J
b11 E
b11 @
1;
1'
10
#2050000
00
#2055000
0'
0&
0;
b100 @
b100 E
b100 J
b100 O
b100 T
10
#2060000
00
#2065000
b101 T
b101 O
b101 J
b101 E
1%
b0 @
1;
1'
10
#2070000
00
#2075000
0'
1&
0;
b1 @
b110 E
b110 J
b110 O
b110 T
10
#2080000
00
#2085000
b111 T
b111 O
b111 J
b111 E
b10 @
1;
1'
10
#2090000
00
#2095000
0'
0&
0;
b11 @
b1000 E
b1000 J
b1000 O
b1000 T
10
#2100000
00
#2105000
b1001 T
b1001 O
b1001 J
b1001 E
b100 @
1;
1'
10
#2110000
00
#2115000
0'
1&
0;
0%
b0 @
1$
b0 E
b1010 J
b1010 O
b1010 T
10
#2120000
00
#2125000
b1011 T
b1011 O
b1011 J
b1 E
b1 @
1;
1'
10
#2130000
00
#2135000
0'
0&
0;
b10 @
b10 E
b1100 J
b1100 O
b1100 T
10
#2140000
00
#2145000
b1101 T
b1101 O
b1101 J
b11 E
b11 @
1;
1'
10
#2150000
00
#2155000
0'
1&
0;
b100 @
b100 E
b1110 J
b1110 O
b1110 T
10
#2160000
00
#2165000
b1111 T
b1111 O
b1111 J
b101 E
1%
b0 @
1;
1'
10
#2170000
00
#2175000
0'
0&
0;
b1 @
b110 E
b10000 J
b10000 O
b10000 T
10
#2180000
00
#2185000
b10001 T
b10001 O
b10001 J
b111 E
b10 @
1;
1'
10
#2190000
00
#2195000
0'
1&
0;
b11 @
b1000 E
b10010 J
b10010 O
b10010 T
10
#2200000
00
#2205000
b10011 T
b10011 O
b10011 J
b1001 E
b100 @
1;
1'
10
#2210000
00
